pyreflex/__init__.py
pyreflex/converter.py
pyreflex/hidden_attribute.py
pyreflex/inspection.py
pyreflex/mirror.py
pyreflex/type_attribute.py
pyreflex/pybase/__init__.py
pyreflex/pybase/namedtuple.py
pyreflex/pybase/namedtuple.pyi
pyreflex/pybase/private.py
pyreflex/pybase/pybase.py
pyreflex/pybase/pybase.pyi
pyreflex-0.0.0.0.14.dist-info/LICENSE
pyreflex-0.0.0.0.14.dist-info/METADATA
pyreflex-0.0.0.0.14.dist-info/WHEEL
pyreflex-0.0.0.0.14.dist-info/top_level.txt
pyreflex-0.0.0.0.14.dist-info/RECORD
