Metadata-Version: 2.1
Name: pyreflex
Version: 0.0.0.0.14
Summary: A tiny project that contains reflection functions.
Author-email: Caewinix <Caewinix@yeah.net>
Project-URL: Homepage, https://github.com/Caewinix/pyreflex
Project-URL: Bug Tracker, https://github.com/Caewinix/pyreflex/issues
Classifier: Programming Language :: Python :: 3
Classifier: License :: OSI Approved :: MIT License
Classifier: Operating System :: OS Independent
Requires-Python: >=3.8
License-File: LICENSE
